{
  "articol": "3153",
  "articol_title": "Mecanism special pentru declararea și plata TVA la import",
  "titlu_id": "VII",
  "titlu_name": "Titlul VII - Taxa pe valoarea adăugată",
  "capitol_id": "XII",
  "capitol_name": "Capitolul XII - Regimuri speciale",
  "sectiune_id": "",
  "sectiune_name": "",
  "section_path": "Titlul VII > Cap. XII > Art. 3153",
  "text": "(1) În situația în care pentru importul bunurilor, cu excepția produselor care fac obiectul accizelor, în loturi cu o valoare intrinsecă de maximum 150 euro, nu se utilizează regimul special prevăzut la art. 3152, persoana care prezintă bunurile în vamă în numele persoanei căreia îi sunt destinate acestea pe teritoriul României poate să utilizeze mecanismul special pentru declararea și plata TVA la import, pe baza autorizației emise de autoritatea vamală competentă și sub rezerva constituirii unei garanții, în cazul acelor bunuri pentru care expedierea sau transportul se încheie în România.\n\n(2) În sensul prezentului articol, se aplică următoarele dispoziții:\n\na) persoana destinatară a bunurilor este obligată la plata TVA;\n\nb) persoana care prezintă bunurile în vamă pe teritoriul României încasează TVA de la persoana destinatară a bunurilor și efectuează plata taxei.\n\n(3) În sensul alin. (2) lit. b) se consideră că o persoană prezintă bunurile în vamă în numele persoanei căreia îi sunt destinate acestea pe teritoriul României, dacă persoana care prezintă bunurile în vamă își declară intenția de a utiliza mecanismul special pentru declararea și plata TVA la import și de a încasa TVA de la persoana căreia îi sunt destinate bunurile. Persoana impozabilă respectivă declară momentul în care își începe sau își încetează activitatea în cadrul prezentului mecanism special sau momentul în care își modifică respectiva activitate astfel încât nu mai îndeplinește condițiile necesare pentru a utiliza prezentul mecanism special. În cazul în care România este statul membru de înregistrare, informațiile respective sunt comunicate pe cale electronică autorității vamale competente.\n\n(4) Prin excepție de la art. 291 alin. (2) și (3), pentru importurile de bunuri realizate în cadrul mecanismului special pentru declararea și plata TVA la import, este aplicabilă cota standard de TVA prevăzută la art. 291 alin. (1).\n\n(5) În situația în care România este statul de import, persoana care prezintă bunurile în vamă trebuie să depună lunar la autoritatea vamală competentă, în format electronic, o declarație specială de TVA lunară. Declarația specială de TVA trebuie să conțină informații referitoare la valoarea totală a TVA încasată în luna calendaristică de raportare. Normele privind autorizarea și utilizarea mecanismului special pentru declararea și plata TVA la import, modelul și conținutul declarației speciale de TVA se aprobă prin ordin al președintelui ANAF.\n\n(6) Persoana care prezintă bunurile în vamă trebuie să depună declarația specială de TVA și să plătească TVA încasată în luna calendaristică de raportare până la termenul de plată aplicabil plății taxelor la import care fac obiectul amânării plății, respectiv cel târziu în a șaisprezecea zi a lunii următoare lunii calendaristice de raportare.\n\n(7) Persoanele care utilizează prezentul mecanism special trebuie să ține registre ale operațiunilor reglementate de acest mecanism special. Registrele respective trebuie să conțină informații care să permită autorităților fiscale sau vamale din România să determine dacă declarația specială de TVA prevăzută la art. 3153 alin. (5) este corectă. Aceste registre se pun la dispoziție, la cerere, pe cale electronică și se păstrează pe o perioadă de 10 ani de la încheierea anului în care s-au efectuat operațiunile.",
  "norme_text": "Norme metodologice",
  "cross_references": [
    "art. 291",
    "art. 3152"
  ],
  "is_abrogated": false
}