{
  "articol": "441",
  "articol_title": "Exigibilitatea",
  "titlu_id": "VIII",
  "titlu_name": "Titlul VIII - Accize și alte taxe speciale",
  "capitol_id": "II",
  "capitol_name": "Capitolul II - Regimul accizelor nearmonizate",
  "sectiune_id": "",
  "sectiune_name": "",
  "section_path": "Titlul VIII > Cap. II > Art. 441",
  "text": "Momentul exigibilității accizelor intervine:\n\na) la data recepționării produselor provenite din achiziții intracomunitare;\n\nb) la data efectuării formalităților de punere în liberă circulație a produselor provenite din operațiuni de import;\n\nc) la data vânzării pe piața internă a produselor provenite din producția internă.",
  "norme_text": "",
  "cross_references": [],
  "is_abrogated": false
}