{
  "articol": "200",
  "articol_title": "\\*\\*\\* A B R O G A T \\*\\*\\*",
  "titlu_id": "V",
  "titlu_name": "Titlul V - Contribuții sociale obligatorii",
  "capitol_id": "V",
  "capitol_name": "Capitolul V - \\*\\*\\* A B R O G A T \\*\\*\\*",
  "sectiune_id": "a 3-a - \\*\\*\\* A B R O G A T Ă \\*\\*\\*",
  "sectiune_name": "SECȚIUNEA a 3-a - \\*\\*\\* A B R O G A T Ă \\*\\*\\*",
  "section_path": "Titlul V > Cap. V > Secț. a 3-a - \\*\\*\\* A B R O G A T Ă \\*\\*\\* > Art. 200",
  "text": "",
  "norme_text": "",
  "cross_references": [],
  "is_abrogated": true
}