{
  "articol": "132",
  "articol_title": "Obligații declarative ale plătitorilor de venituri cu reținere la sursă",
  "titlu_id": "IV",
  "titlu_name": "Titlul IV - Impozitul pe venit",
  "capitol_id": "XIV",
  "capitol_name": "Capitolul XIV - Obligații declarative ale plătitorilor de venituri cu reținere la sursă",
  "sectiune_id": "",
  "sectiune_name": "",
  "section_path": "Titlul IV > Cap. XIV > Art. 132",
  "text": "(1) Plătitorii de venituri, cu regim de reținere la sursă a impozitelor, sunt obligați să calculeze, să rețină, să plătească și să declare impozitul reținut la sursă, până la termenul de plată a acestuia inclusiv.\n\n(2) Plătitorii de venituri cu regim de reținere la sursă a impozitelor au obligația să depună o declarație privind calcularea și reținerea impozitului pentru fiecare beneficiar de venit la organul fiscal competent, până în ultima zi a lunii februarie inclusiv a anului curent pentru anul expirat, cu excepția plătitorilor de venituri din salarii și asimilate salariilor, plătitorilor de venituri din pensii, plătitorilor de venituri din drepturi de proprietate intelectuală, plătitorilor de venituri în baza contractelor de activitate sportivă, venituri din arendă sau din asocieri cu persoane juridice, aceștia având obligația depunerii Declarației privind obligațiile de plată a contribuțiilor sociale, impozitului pe venit și evidența nominală a persoanelor asigurate.\n\nACTE NORMATIVE\n\nOrdinul președintelui Agenției Naționale de Administrare Fiscală nr. 3695/2016 din 27 decembrie 2016 pentru aprobarea formularelor privind definitivarea impozitului anual pe venit și a contribuțiilor sociale datorate de persoanele fizice\n\nOrdinul președintelui Agenției Naționale de Administrare Fiscală nr. 3726/2017 pentru modificarea și completarea Ordinului președintelui Agenției Naționale de Administrare Fiscală nr. 3695/2016 pentru aprobarea formularelor privind definitivarea impozitului anual pe venit și a contribuțiilor sociale datorate de persoanele fizice.\n\nOrdinul președintelui Agenției Naționale de Administrare Fiscală nr. 48/2019 pentru aprobarea modelului și conținutului formularelor 205 \"Declarație informativă privind impozitul reținut la sursă și câștigurile/pierderile din investiții, pe beneficiari de venit\" și 207 \"Declarație informativă privind impozitul reținut la sursă/veniturile scutite, pe beneficiari de venit nerezidenți\"\n\n(3) Prevederile alin. (2) sunt aplicabile și în cazul plătitorilor de venituri prevăzuți la art. 841 alin. (9) pentru veniturile prevăzute la art. 841 alin. (8).",
  "norme_text": "",
  "cross_references": [
    "art. 841"
  ],
  "is_abrogated": false
}