{
  "articol": "472",
  "articol_title": "Plata impozitului",
  "titlu_id": "IX",
  "titlu_name": "Titlul IX - Impozite și taxe locale",
  "capitol_id": "IV",
  "capitol_name": "Capitolul IV - Impozitul pe mijloacele de transport",
  "sectiune_id": "",
  "sectiune_name": "",
  "section_path": "Titlul IX > Cap. IV > Art. 472",
  "text": "",
  "norme_text": "(1) Impozitul pe mijlocul de transport se plătește anual, în două rate egale, până la datele de 31 martie și 30 septembrie inclusiv. Norme metodologice\n\n(2) Pentru plata cu anticipație a impozitului pe mijlocul de transport, datorat pentru întregul an de către contribuabili, până la data de 31 martie a anului respectiv inclusiv, se acordă o bonificație de până la 10% inclusiv, stabilită prin hotărâre a consiliului local. La nivelul municipiului București, această atribuție revine Consiliului General al Municipiului București.\n\n(3) Impozitul anual pe mijlocul de transport, datorat aceluiași buget local de către contribuabili, persoane fizice și juridice, de până la 50 lei inclusiv, se plătește integral până la primul termen de plată. În cazul în care contribuabilul deține în proprietate mai multe mijloace de transport, pentru care impozitul este datorat bugetului local al aceleiași unități administrativ-teritoriale, suma de 50 lei se referă la impozitul pe mijlocul de transport cumulat al acestora.",
  "cross_references": [],
  "is_abrogated": false
}