{
  "articol": "492",
  "articol_title": "Elaborarea normelor",
  "titlu_id": "IX",
  "titlu_name": "Titlul IX - Impozite și taxe locale",
  "capitol_id": "X",
  "capitol_name": "Capitolul X - Alte dispoziții comune",
  "sectiune_id": "",
  "sectiune_name": "",
  "section_path": "Titlul IX > Cap. X > Art. 492",
  "text": "Elaborarea normelor pentru prezentul titlu se face de către Ministerul Finanțelor Publice și Ministerul Dezvoltării Regionale și Administrației Publice.",
  "norme_text": "",
  "cross_references": [],
  "is_abrogated": false
}