{
  "articol": "337",
  "articol_title": "Teritorii terțe",
  "titlu_id": "VIII",
  "titlu_name": "Titlul VIII - Accize și alte taxe speciale",
  "capitol_id": "I",
  "capitol_name": "Capitolul I - Regimul accizelor armonizate",
  "sectiune_id": "1 - Dispoziții generale",
  "sectiune_name": "SECȚIUNEA 1 - Dispoziții generale",
  "section_path": "Titlul VIII > Cap. I > Secț. 1 - Dispoziții generale > Art. 337",
  "text": "(1) Sunt considerate teritorii terțe următoarele teritorii care fac parte din teritoriul vamal al Uniunii Europene:\n\na) insulele Canare;\n\nb) teritoriile franceze menționate la art. 349 și art. 355 alin. (1) din Tratatul privind funcționarea Uniunii Europene;\n\nc) insulele Aland;\n\nd) insulele Anglo-Normande (Channel Islands).\n\n(2) Sunt considerate teritorii terțe și teritoriile care intră sub incidența art. 355 alin. (3) din Tratatul privind funcționarea Uniunii Europene, precum și următoarele teritorii care nu fac parte din teritoriul vamal al Uniunii Europene:\n\na) insula Helgoland;\n\nb) teritoriul Busingen;\n\nc) Ceuta;\n\nd) Melilla;\n\ne) Livigno;\n\nf) *** A B R O G A T ***\n\ng) *** A B R O G A T ***\n\n(3) Operațiunile cu produse accizabile efectuate provenind din sau având ca destinație:\n\na) Principatul Monaco sunt tratate ca deplasări dinspre sau către Franța;\n\nb) San Marino sunt tratate ca deplasări dinspre sau către Italia;\n\nc) zonele Akrotiri și Dhekelia aflate sub suveranitatea Regatului Unit sunt tratate ca deplasări dinspre sau către Cipru;\n\nd) insula Man sunt tratate ca deplasări dinspre sau către Regatul Unit;\n\ne) Jungholz și Mittelberg (Kleines Walsertal) sunt tratate ca deplasări dinspre sau către Germania.\n\n(4) **** A B R O G A T ****\n\n(5) **** A B R O G A T ****",
  "norme_text": "",
  "cross_references": [
    "art. 349",
    "art. 355"
  ],
  "is_abrogated": true
}